sql_metadata/__init__.py
sql_metadata/compat.py
sql_metadata/generalizator.py
sql_metadata/keywords_lists.py
sql_metadata/parser.py
sql_metadata/token.py
sql_metadata/utils.py
sql_metadata_fork-2.3.0.dist-info/LICENSE
sql_metadata_fork-2.3.0.dist-info/WHEEL
sql_metadata_fork-2.3.0.dist-info/METADATA
sql_metadata_fork-2.3.0.dist-info/RECORD
