Metadata-Version: 2.1
Name: sql-metadata-fork
Version: 2.3.0
Summary: Uses tokenized query returned by python-sqlparse and generates query metadata
Home-page: https://github.com/macbre/sql-metadata
License: MIT
Author: Maciej Brencz
Author-email: maciej.brencz@gmail.com
Requires-Python: >=3.6.2,<4.0.0
Classifier: License :: OSI Approved :: MIT License
Classifier: Programming Language :: Python :: 3
Classifier: Programming Language :: Python :: 3.10
Classifier: Programming Language :: Python :: 3.7
Classifier: Programming Language :: Python :: 3.8
Classifier: Programming Language :: Python :: 3.9
Requires-Dist: sqlparse (>=0.4.1,<0.5.0)
Project-URL: Repository, https://github.com/macbre/sql-metadata
